{
	"info": {
		"_postman_id": "b37edb17-2c90-426f-af8d-6956e4dd7969",
		"name": "petfriend unit 8.5",
		"schema": "https://schema.getpostman.com/json/collection/v2.1.0/collection.json",
		"_exporter_id": "24262511"
	},
	"item": [
		{
			"name": "key",
			"event": [
				{
					"listen": "test",
					"script": {
						"exec": [
							"\r",
							"pm.test(\"Status test\", function () {\r",
							"    pm.response.to.have.status(200);\r",
							"});\r",
							"var jsonData = JSON.parse(responseBody);\r",
							"pm.collectionVariables.set(\"auth_key\", jsonData.key);"
						],
						"type": "text/javascript"
					}
				}
			],
			"protocolProfileBehavior": {
				"disableBodyPruning": true
			},
			"request": {
				"method": "GET",
				"header": [
					{
						"key": "password",
						"value": "nky2Y2atBRE7WsY",
						"type": "text"
					},
					{
						"key": "email",
						"value": "imps9870@gmail.com",
						"type": "text"
					}
				],
				"body": {
					"mode": "formdata",
					"formdata": []
				},
				"url": {
					"raw": "{{url}}/api/key",
					"host": [
						"{{url}}"
					],
					"path": [
						"api",
						"key"
					]
				}
			},
			"response": []
		},
		{
			"name": "createpet",
			"event": [
				{
					"listen": "test",
					"script": {
						"exec": [
							"pm.test(\"Status code is 200\", function () {\r",
							"    pm.response.to.have.status(200);\r",
							"    var jsonData = JSON.parse(responseBody);\r",
							"    pm.collectionVariables.set(\"petid\", jsonData.id);\r",
							"});"
						],
						"type": "text/javascript"
					}
				}
			],
			"request": {
				"method": "POST",
				"header": [
					{
						"key": "password",
						"value": "nky2Y2atBRE7WsY",
						"type": "text",
						"disabled": true
					},
					{
						"key": "email",
						"value": "imps9870@gmail.com",
						"type": "text",
						"disabled": true
					}
				],
				"body": {
					"mode": "formdata",
					"formdata": [
						{
							"key": "name",
							"value": "{{name}}",
							"type": "text"
						},
						{
							"key": "age",
							"value": "{{age}}",
							"type": "text"
						},
						{
							"key": "type",
							"value": "{{type}}",
							"type": "text"
						}
					]
				},
				"url": {
					"raw": "https://petfriends.skillfactory.ru/api/create_pet_simple",
					"protocol": "https",
					"host": [
						"petfriends",
						"skillfactory",
						"ru"
					],
					"path": [
						"api",
						"create_pet_simple"
					]
				}
			},
			"response": []
		}
	],
	"auth": {
		"type": "apikey",
		"apikey": [
			{
				"key": "value",
				"value": "{{auth_key}}",
				"type": "string"
			},
			{
				"key": "key",
				"value": "auth_key",
				"type": "string"
			}
		]
	},
	"event": [
		{
			"listen": "prerequest",
			"script": {
				"type": "text/javascript",
				"exec": [
					""
				]
			}
		},
		{
			"listen": "test",
			"script": {
				"type": "text/javascript",
				"exec": [
					""
				]
			}
		}
	],
	"variable": [
		{
			"key": "auth_key",
			"value": "",
			"type": "string"
		},
		{
			"key": "url",
			"value": "https://petfriends.skillfactory.ru",
			"type": "string"
		},
		{
			"key": "name",
			"value": "",
			"type": "string"
		},
		{
			"key": "age",
			"value": "",
			"type": "string"
		},
		{
			"key": "type",
			"value": "",
			"type": "string"
		},
		{
			"key": "petid",
			"value": "",
			"type": "string"
		}
	]
}